.coveragerc
.gitignore
LICENSE
README.md
pyproject.toml
setup.cfg
setup.py
tox.ini
demo/demo.ipynb
media/cluster_results.png
src/finch/__init__.py
src/finch/finch.py
src/finchpy.egg-info/PKG-INFO
src/finchpy.egg-info/SOURCES.txt
src/finchpy.egg-info/dependency_links.txt
src/finchpy.egg-info/not-zip-safe
src/finchpy.egg-info/requires.txt
src/finchpy.egg-info/top_level.txt