Metadata-Version: 2.1
Name: finchpy
Version: 0.0.1
Summary: FINCH - First Integer Neighbor Clustering Hierarchy Algorithm
Home-page: https://github.com/eren-ck/finch
Author: Eren Cakmak
Author-email: 22754816+eren-ck@users.noreply.github.com
License: License :: OSI Approved :: MIT License
Project-URL: Documentation, https://pyscaffold.org/
Platform: any
Classifier: Development Status :: 4 - Beta
Classifier: Intended Audience :: Science/Research
Classifier: Intended Audience :: Developers
Classifier: License :: OSI Approved :: MIT License
Classifier: Programming Language :: Python
Classifier: Programming Language :: Python :: 3
Classifier: Programming Language :: Python :: 3.5
Classifier: Programming Language :: Python :: 3.6
Classifier: Programming Language :: Python :: 3.7
Classifier: Programming Language :: Python :: 3.8
Classifier: Topic :: Software Development
Classifier: Topic :: Scientific/Engineering
Classifier: Operating System :: Microsoft :: Windows
Classifier: Operating System :: Unix
Classifier: Operating System :: MacOS
Provides-Extra: testing
